mcp_jupyter/__init__.py
mcp_jupyter/__main__.py
mcp_jupyter/notebook.py
mcp_jupyter/rest_client.py
mcp_jupyter/server.py
mcp_jupyter/state.py
mcp_jupyter/utils.py
mcp_jupyter-2.0.2.dist-info/METADATA
mcp_jupyter-2.0.2.dist-info/WHEEL
mcp_jupyter-2.0.2.dist-info/entry_points.txt
mcp_jupyter-2.0.2.dist-info/licenses/LICENSE
mcp_jupyter-2.0.2.dist-info/RECORD
