Metadata-Version: 2.4
Name: mcp-jupyter
Version: 2.0.2
Summary: MCP Jupyter
License-File: LICENSE
Requires-Python: >=3.10
Requires-Dist: beautifulsoup4>=4.12.3
Requires-Dist: jupyter-kernel-client>=0.8.0
Requires-Dist: mcp[cli]>=1.13.1
Requires-Dist: requests>=2.32.3
Requires-Dist: rich
